luxpy/__init__.py
luxpy/desktop.ini
luxpy/color/CDATA.py
luxpy/color/__init__.py
luxpy/color/cam/__init__.py
luxpy/color/cam/cam02ucs.py
luxpy/color/cam/cam15u.py
luxpy/color/cam/cam16ucs.py
luxpy/color/cam/cam18sl.py
luxpy/color/cam/camjabz.py
luxpy/color/cam/ciecam02.py
luxpy/color/cam/ciecam16.py
luxpy/color/cam/cmf_translator_sww2021.py
luxpy/color/cam/colorappearancemodels.py
luxpy/color/cam/helpers.py
luxpy/color/cam/sww2016.py
luxpy/color/cam/utils.py
luxpy/color/cam/zcam.py
luxpy/color/cam/zcam_bak.py
luxpy/color/cat/__init__.py
luxpy/color/cat/chromaticadaptation.py
luxpy/color/cct/__init__.py
luxpy/color/cct/cct.py
luxpy/color/cct/cct_bruteforce.py
luxpy/color/cct/cct_legacy.py
luxpy/color/cct/cctduv_ohno_CORM2011.py
luxpy/color/cct/robertson1968/__init__.py
luxpy/color/cct/robertson1968/robertson1968.py
luxpy/color/cct/robertson1968/luts/CMFs_360-830-1.pkl
luxpy/color/cct/robertson1968/luts/robertson1968.pkl
luxpy/color/cri/__init__.py
luxpy/color/cri/colorrendition.py
luxpy/color/cri/VFPX/VF_PX_models.py
luxpy/color/cri/VFPX/__init__.py
luxpy/color/cri/VFPX/pixelshiftmodel.py
luxpy/color/cri/VFPX/vectorshiftmodel.py
luxpy/color/cri/iestm30/__init__.py
luxpy/color/cri/iestm30/cvg_background.jfif
luxpy/color/cri/iestm30/graphics.py
luxpy/color/cri/iestm30/metrics.py
luxpy/color/cri/iestm30/metrics_fast.py
luxpy/color/cri/iestm30/testfig.png
luxpy/color/cri/indices/__init__.py
luxpy/color/cri/indices/cie_wrappers.py
luxpy/color/cri/indices/cqs.py
luxpy/color/cri/indices/cri2012.py
luxpy/color/cri/indices/fci.py
luxpy/color/cri/indices/iestm30_wrappers.py
luxpy/color/cri/indices/indices.py
luxpy/color/cri/indices/mcri.py
luxpy/color/cri/indices/thorntoncpi.py
luxpy/color/cri/utils/DE_scalers.py
luxpy/color/cri/utils/__init__.py
luxpy/color/cri/utils/cvg_background.jfif
luxpy/color/cri/utils/graphics.py
luxpy/color/cri/utils/helpers.py
luxpy/color/cri/utils/init_cri_defaults_database.py
luxpy/color/ctf/__init__.py
luxpy/color/ctf/colortf.py
luxpy-1.12.0.dist-info/LICENSE.md
luxpy-1.12.0.dist-info/METADATA
luxpy-1.12.0.dist-info/WHEEL
luxpy-1.12.0.dist-info/top_level.txt
luxpy-1.12.0.dist-info/RECORD
